dwd_opendata/__init__.py
dwd_opendata/py.typed
dwd_opendata/tests/test_dwd_opendata.py
dwd_opendata/tests/test_integration.py
dwd_opendata-0.1.0.dist-info/METADATA
dwd_opendata-0.1.0.dist-info/WHEEL
dwd_opendata-0.1.0.dist-info/licenses/LICENCE
dwd_opendata-0.1.0.dist-info/licenses/LICENSE
dwd_opendata-0.1.0.dist-info/RECORD
