Metadata-Version: 2.4
Name: dwd_opendata
Version: 0.1.0
Summary: Download data from DWD's ftp server and return it as xarray DataArray
Author-email: iskur <32363199+iskur@users.noreply.github.com>
License: MIT
License-File: LICENCE
License-File: LICENSE
Requires-Python: >=3.13
Requires-Dist: cartopy>=0.24.1
Requires-Dist: pandas>=2.3.0
Requires-Dist: tqdm>=4.67.1
Requires-Dist: xarray>=2024.1.0
Provides-Extra: plot
Requires-Dist: cartopy>=0.24.1; extra == 'plot'
